cem/__init__.py
cem/coarsen.py
cem/imbalance.py
cem/match.py
cem-1.0.0.dist-info/LICENSE
cem-1.0.0.dist-info/METADATA
cem-1.0.0.dist-info/WHEEL
cem-1.0.0.dist-info/RECORD
