Metadata-Version: 2.1
Name: cem
Version: 1.0.0
Summary: Coarsened Exact Matching for Causal Inference
Author: Lewis Bails
Author-email: lewis.bails@gmail.com
Requires-Python: >=3.9,<3.13
Classifier: Programming Language :: Python :: 3
Classifier: Programming Language :: Python :: 3.9
Classifier: Programming Language :: Python :: 3.10
Classifier: Programming Language :: Python :: 3.11
Requires-Dist: numpy (>=1.26.0,<2.0.0)
Requires-Dist: pandas (>=2.1.0,<3.0.0)
